AUTHORS
MANIFEST.in
setup.py
django_pipeline_compass.egg-info/PKG-INFO
django_pipeline_compass.egg-info/SOURCES.txt
django_pipeline_compass.egg-info/dependency_links.txt
django_pipeline_compass.egg-info/not-zip-safe
django_pipeline_compass.egg-info/requires.txt
django_pipeline_compass.egg-info/top_level.txt
pipeline_compass/__init__.py
pipeline_compass/compiler.py
pipeline_compass/compass/LICENSE.markdown
pipeline_compass/compass/README.txt
pipeline_compass/compass/_compass.scss
pipeline_compass/compass/_lemonade.scss
pipeline_compass/compass/compass/_css3.scss
pipeline_compass/compass/compass/_layout.scss
pipeline_compass/compass/compass/_reset-legacy.scss
pipeline_compass/compass/compass/_reset.scss
pipeline_compass/compass/compass/_support.scss
pipeline_compass/compass/compass/_typography.scss
pipeline_compass/compass/compass/_utilities.scss
pipeline_compass/compass/compass/css3/_appearance.scss
pipeline_compass/compass/compass/css3/_background-clip.scss
pipeline_compass/compass/compass/css3/_background-origin.scss
pipeline_compass/compass/compass/css3/_background-size.scss
pipeline_compass/compass/compass/css3/_border-radius.scss
pipeline_compass/compass/compass/css3/_box-shadow.scss
pipeline_compass/compass/compass/css3/_box-sizing.scss
pipeline_compass/compass/compass/css3/_box.scss
pipeline_compass/compass/compass/css3/_columns.scss
pipeline_compass/compass/compass/css3/_font-face.scss
pipeline_compass/compass/compass/css3/_gradient.scss
pipeline_compass/compass/compass/css3/_images.scss
pipeline_compass/compass/compass/css3/_inline-block.scss
pipeline_compass/compass/compass/css3/_opacity.scss
pipeline_compass/compass/compass/css3/_pie.scss
pipeline_compass/compass/compass/css3/_shared.scss
pipeline_compass/compass/compass/css3/_text-shadow.scss
pipeline_compass/compass/compass/css3/_transform-legacy.scss
pipeline_compass/compass/compass/css3/_transform.scss
pipeline_compass/compass/compass/css3/_transition.scss
pipeline_compass/compass/compass/css3/_user-interface.scss
pipeline_compass/compass/compass/layout/_grid-background.scss
pipeline_compass/compass/compass/layout/_sticky-footer.scss
pipeline_compass/compass/compass/layout/_stretching.scss
pipeline_compass/compass/compass/reset/_utilities-legacy.scss
