Metadata-Version: 1.0
Name: django-pipeline-compass
Version: 0.1.1
Summary: 
